Metadata-Version: 1.1
Name: Mapp
Version: 0.1.0
Summary: Package for simplify MAPP prediction analysis workflow.
Home-page: http://pypi.python.org/pypi/Mapp/
Author: Ondrej Pelikan
Author-email: onpelikan@gmail.com
License: LICENSE.txt
Platform: UNKNOWN
Classifier: Development Status :: 5 - Production/Stable
Classifier: Intended Audience :: Developers
Classifier: Natural Language :: English
Classifier: License :: OSI Approved :: GNU Lesser General Public License v3 (LGPLv3)
Classifier: Operating System :: OS Independent
Classifier: Programming Language :: Python
Classifier: Programming Language :: Python :: 2
Classifier: Programming Language :: Python :: 2.6
Classifier: Programming Language :: Python :: 2.7
Classifier: Topic :: Software Development :: Libraries :: Python Modules
